<Signature xmlns="http://www.w3.org/2000/09/xmldsig#" Id="DistributorSignature">
<SignedInfo>
<CanonicalizationMethod Algorithm="http://www.w3.org/2001/10/xml-exc-c14n#"></CanonicalizationMethod>
<SignatureMethod Algorithm="http://www.w3.org/2001/04/xmldsig-more#rsa-sha256"></SignatureMethod>
<Reference URI="author-signature.xml">
<DigestMethod Algorithm="http://www.w3.org/2001/04/xmlenc#sha256"></DigestMethod>
<DigestValue>evleaN8s6lcHzTADlml+5+dQyykV3uR61mR5Wm4B9ro=</DigestValue>
</Reference>
<Reference URI="bin%2Fbubble">
<DigestMethod Algorithm="http://www.w3.org/2001/04/xmlenc#sha256"></DigestMethod>
<DigestValue>8NAQfh8eMCItwFAZ3vsHq9XXjwzdlGIULOiglpyt0XM=</DigestValue>
</Reference>
<Reference URI="res%2F0.png">
<DigestMethod Algorithm="http://www.w3.org/2001/04/xmlenc#sha256"></DigestMethod>
<DigestValue>ehJ0VqjKXuh4jtWvb78gxeS7/rxMVcUmvCbrr74CDYM=</DigestValue>
</Reference>
<Reference URI="res%2F1.png">
<DigestMethod Algorithm="http://www.w3.org/2001/04/xmlenc#sha256"></DigestMethod>
<DigestValue>eRF1tDWsLIi7ATSIqFqznhAsU9v6+pMmCFYq6u45RX4=</DigestValue>
</Reference>
<Reference URI="res%2F2.png">
<DigestMethod Algorithm="http://www.w3.org/2001/04/xmlenc#sha256"></DigestMethod>
<DigestValue>JiJaZw3eLC1G3QdtWq+TmyQvVfk5WVxbyoXS9VTiXCs=</DigestValue>
</Reference>
<Reference URI="res%2F3.png">
<DigestMethod Algorithm="http://www.w3.org/2001/04/xmlenc#sha256"></DigestMethod>
<DigestValue>0/cX5+v74ySnTr3n9/ckgSWRfYHSO1lVpkgdjK7vANQ=</DigestValue>
</Reference>
<Reference URI="res%2F4.png">
<DigestMethod Algorithm="http://www.w3.org/2001/04/xmlenc#sha256"></DigestMethod>
<DigestValue>ixlZ2VrekaXP7Cx3qlTEzJNxJJHPx4pbbDkFE8zsqTk=</DigestValue>
</Reference>
<Reference URI="res%2F5.png">
<DigestMethod Algorithm="http://www.w3.org/2001/04/xmlenc#sha256"></DigestMethod>
<DigestValue>KrBW72wod7TXbJEcssP1Ubpu7lWSzOCix2du+z5+3IE=</DigestValue>
</Reference>
<Reference URI="res%2Farrow_left.png">
<DigestMethod Algorithm="http://www.w3.org/2001/04/xmlenc#sha256"></DigestMethod>
<DigestValue>oYm3bOX7LxJGscVvXWoAqAmkzvALmv5yxh/faKakNhg=</DigestValue>
</Reference>
<Reference URI="res%2Farrow_right.png">
<DigestMethod Algorithm="http://www.w3.org/2001/04/xmlenc#sha256"></DigestMethod>
<DigestValue>FybTFGGxSMFVIYDwfplcGwLVH6In2hRhbcEZpF2Pe1g=</DigestValue>
</Reference>
<Reference URI="res%2FbigHeart.png">
<DigestMethod Algorithm="http://www.w3.org/2001/04/xmlenc#sha256"></DigestMethod>
<DigestValue>fElPKDmo0F6bcIVo79Wl2M2e4e4bNS8H8ccE341sYvc=</DigestValue>
</Reference>
<Reference URI="res%2Fbubble_not_popped.png">
<DigestMethod Algorithm="http://www.w3.org/2001/04/xmlenc#sha256"></DigestMethod>
<DigestValue>qfxwGMrKMTIKQksnqaJcPPG5UUNmZkBbBUX0QABbItk=</DigestValue>
</Reference>
<Reference URI="res%2Fbubble_pop.wav">
<DigestMethod Algorithm="http://www.w3.org/2001/04/xmlenc#sha256"></DigestMethod>
<DigestValue>MX5ZBikOTzZUAN2AGwew2uVvFeiEOO0f8TWTExf7ymw=</DigestValue>
</Reference>
<Reference URI="res%2Fbubble_popped.png">
<DigestMethod Algorithm="http://www.w3.org/2001/04/xmlenc#sha256"></DigestMethod>
<DigestValue>9OWYblnn8S4bnzR6HQ1vLN/+Mz89lq3rhVsEjQbYz0Y=</DigestValue>
</Reference>
<Reference URI="res%2Fbug.png">
<DigestMethod Algorithm="http://www.w3.org/2001/04/xmlenc#sha256"></DigestMethod>
<DigestValue>lkPvVoeZsitKzJjfyqe+a9GV5RuhpN4CKbdfoZdF9vk=</DigestValue>
</Reference>
<Reference URI="res%2Fexit.png">
<DigestMethod Algorithm="http://www.w3.org/2001/04/xmlenc#sha256"></DigestMethod>
<DigestValue>OvU8DzhcXXi+b6UTeaKDiEFjWYEOpZpETG6mMndNiXA=</DigestValue>
</Reference>
<Reference URI="res%2Fheart.png">
<DigestMethod Algorithm="http://www.w3.org/2001/04/xmlenc#sha256"></DigestMethod>
<DigestValue>0OiSjMmZt48bUF1owN0qTSL7b4o2OK4iHtQSXUWx0Zw=</DigestValue>
</Reference>
<Reference URI="res%2Fheart2.png">
<DigestMethod Algorithm="http://www.w3.org/2001/04/xmlenc#sha256"></DigestMethod>
<DigestValue>fElPKDmo0F6bcIVo79Wl2M2e4e4bNS8H8ccE341sYvc=</DigestValue>
</Reference>
<Reference URI="res%2Fhurdle.png">
<DigestMethod Algorithm="http://www.w3.org/2001/04/xmlenc#sha256"></DigestMethod>
<DigestValue>YDVaZ+tqQ4h++t5swd+onKqrE2ssuey8ul40HDO4dZo=</DigestValue>
</Reference>
<Reference URI="res%2Fhurdle2.png">
<DigestMethod Algorithm="http://www.w3.org/2001/04/xmlenc#sha256"></DigestMethod>
<DigestValue>iXAsWWo60y/W52Mxl0uSBBQTMw/95eRm1UgmABM+b5g=</DigestValue>
</Reference>
<Reference URI="res%2Fjump.png">
<DigestMethod Algorithm="http://www.w3.org/2001/04/xmlenc#sha256"></DigestMethod>
<DigestValue>c5rTac7LemABF24DaTVLOSW/p6qR6qs8T/15xgLQdsc=</DigestValue>
</Reference>
<Reference URI="res%2Fobstacle.png">
<DigestMethod Algorithm="http://www.w3.org/2001/04/xmlenc#sha256"></DigestMethod>
<DigestValue>iXAsWWo60y/W52Mxl0uSBBQTMw/95eRm1UgmABM+b5g=</DigestValue>
</Reference>
<Reference URI="res%2Franking.txt">
<DigestMethod Algorithm="http://www.w3.org/2001/04/xmlenc#sha256"></DigestMethod>
<DigestValue>pAX7SHx24lxxaeCGRWs5Td8w5WIhwR/UERzQQeieaKc=</DigestValue>
</Reference>
<Reference URI="res%2Fsave.png">
<DigestMethod Algorithm="http://www.w3.org/2001/04/xmlenc#sha256"></DigestMethod>
<DigestValue>rxpIUQukLSG5el9yb7lJ8QnRYeH3GZ7dPmh7rJakQVE=</DigestValue>
</Reference>
<Reference URI="res%2Fshake.png">
<DigestMethod Algorithm="http://www.w3.org/2001/04/xmlenc#sha256"></DigestMethod>
<DigestValue>BDo0EVACIDDIoWrHnU3/5mqXi8b7XWMx8/9cGVwEaLA=</DigestValue>
</Reference>
<Reference URI="shared%2Fres%2Fbubble.png">
<DigestMethod Algorithm="http://www.w3.org/2001/04/xmlenc#sha256"></DigestMethod>
<DigestValue>1d0oEZHqPn+QzNzGIHwj9ODby6x9ggFs9uOsav6jPNs=</DigestValue>
</Reference>
<Reference URI="tizen-manifest.xml">
<DigestMethod Algorithm="http://www.w3.org/2001/04/xmlenc#sha256"></DigestMethod>
<DigestValue>5w3B6r3piNe3oT97ZCR05Z4cupabqkgyeGmbhDqHwLE=</DigestValue>
</Reference>
<Reference URI="#prop">
<Transforms>
<Transform Algorithm="http://www.w3.org/2006/12/xml-c14n11"></Transform>
</Transforms>
<DigestMethod Algorithm="http://www.w3.org/2001/04/xmlenc#sha256"></DigestMethod>
<DigestValue>u/jU3U4Zm5ihTMSjKGlGYbWzDfRkGphPPHx3gJIYEJ4=</DigestValue>
</Reference>
</SignedInfo>
<SignatureValue>
kGHgBQbAKX1xZsH+F5WTTmawVHVjdEHpokjL0TTDodrayIRS4HYSBzzO6gRu3LmC9eJKpgPWiTH2
/zNqMA042FC0gRft3FN7VcmAfNBvh4WCvSDNLZI1TCcbM27E036dxjjvdsP9Npjv3l07BtT3Eem6
BGeEHrOumNID5qrVH0aizqcToQhm/HhBEHajsp4qwPNafwW7o+y880hQ7dM7WqrlQuSaWnvnIqab
z+2cDEgGdDZCZEWNqbbsRjudHXKpspFSbRI6A9QKsYy+ZRrevk1CQA/C7rabgdYP2sPhbVWyUmv4
IyQR7b+YC9jfWUnpFzIP++zGIYhZt5vRfARgeQ==
</SignatureValue>
<KeyInfo>
<X509Data>
<X509Certificate>
MIID3TCCAsWgAwIBAgIBZTANBgkqhkiG9w0BAQsFADCBnjELMAkGA1UEBhMCS1IxFDASBgNVBAgM
C1NvdXRoIEtvcmVhMQ4wDAYDVQQHDAVTdXdvbjEmMCQGA1UECgwdU2Ftc3VuZyBFbGVjdHJvbmlj
cyBDby4sIEx0ZC4xDzANBgNVBAsMBk1vYmlsZTEwMC4GA1UEAwwnU2Ftc3VuZyBUaXplbiBERVZF
TE9QRVIgUHVibGljIENBIENsYXNzMB4XDTE4MDUwMTAyNDM0OFoXDTE5MDUwMTAyNDM0OFowazER
MA8GA1UEAwwIVGl6ZW5TREsxCTAHBgNVBAsMADEJMAcGA1UECgwAMQkwBwYDVQQHDAAxCTAHBgNV
BAgMADEJMAcGA1UEBhMAMR8wHQYJKoZIhvcNAQkBFhBqZTIxNTZAc251LmFjLmtyMIIBIjANBgkq
hkiG9w0BAQEFAAOCAQ8AMIIBCgKCAQEAosj2zVcfyzDkAGyx0LpQTgO9c5swmeN9bcP0mhID04cW
hSwv9U6Iy60S7EVxWE8FhYL96CRQQRbu17rT3N4H+dhBo/Lmxgshr0uLm/foHN9JD8f6UYNF25HL
2Rp3Cw9azXA5kUbBuszj1qb4/w9/YAdjnOhXsE5Gx34ycQlFFPmL/SY+XM4W0B/8OOj9d8eEft2x
Ms8KspWqW2hG+KigdWmwb4+KjJKwSWogp+WB9B1s40eTc3aRIsGs5PncniIzak4hunLPXByF2BgZ
R7U9edpWPDhPLnGraI2u8FhptH6bsL9FcTRlUlJG42fqWrGLevyoUw4tlDSvl+MHBHl6dwIDAQAB
o1gwVjBUBgNVHREETTBLhhRVUk46dGl6ZW46cGFja2FnZWlkPYYzVVJOOnRpemVuOmRldmljZWlk
PTIuMCMzWklReG5Gb1VqYkZuTmIrdGZ6endNWVkzdWM9MA0GCSqGSIb3DQEBCwUAA4IBAQCR4kJc
XGLwOdurM/l/2B10MAuzaSnolpphhE7a1iqNkcdxdUeqpd18b/GrmgDrfcG2jHORFb7ZcilZ0AwH
uDIYRgsC6miULYoqUEUZ1QD50N1eZU9GlhP3+wcgwfzS6irXOl1w5pDaltNWE3frBKOuEGp/uAJ9
Wg6j2dKMApH5SHerigu6kWvYh5zojyDXEYGcTwGuEEB7A/yiwgUDnkeWseT7A6Y4YreMb3JtJrfs
5jg0zc1Xprbckv/kKdhz4jpPcTea12N6QFKT0ozZAu5r+eVqJ4q1E8tCKWQndENx4748l4Eu72kz
yT8PPLYlJ6/e2bsf+FLxCVZnhxF8Z+SE
</X509Certificate>
<X509Certificate>
MIIDuzCCAqOgAwIBAgICL+cwDQYJKoZIhvcNAQELBQAwgY8xCzAJBgNVBAYTAktSMRQwEgYDVQQI
DAtTb3V0aCBLb3JlYTEOMAwGA1UEBwwFU3V3b24xJjAkBgNVBAoMHVNhbXN1bmcgRWxlY3Ryb25p
Y3MgQ28uLCBMdGQuMTIwMAYDVQQDDClTYW1zdW5nIFRpemVuIERFVkVMT1BFUiBQdWJsaWMgUm9v
dCBDbGFzczAeFw0xMzEyMzAxNTAxNDdaFw0yODEyMjYxNTAxNDdaMIGeMQswCQYDVQQGEwJLUjEU
MBIGA1UECAwLU291dGggS29yZWExDjAMBgNVBAcMBVN1d29uMSYwJAYDVQQKDB1TYW1zdW5nIEVs
ZWN0cm9uaWNzIENvLiwgTHRkLjEPMA0GA1UECwwGTW9iaWxlMTAwLgYDVQQDDCdTYW1zdW5nIFRp
emVuIERFVkVMT1BFUiBQdWJsaWMgQ0EgQ2xhc3MwggEiMA0GCSqGSIb3DQEBAQUAA4IBDwAwggEK
AoIBAQCkqW9d0zO5NFOc7u164DKe9Yx+yEgUnsbhnJasqHaqT71qaMxyCOjyysZi7gGycDcgmLcU
tr2wSMTGWPibK8SrJ8bV/J1cy9nTpljM3s+lbPIVVxZeufhJkU79tXImHLolERd0vui+rj0Xpd9O
zlyNTRt0+PWVT1taWcbfHL7pUD25hMkTc8C3bC+dUoT1/RhCkXgmUvIor3EnnU0rBtAl4qNtg5y1
7RLT8dyicieAHCcW923YC/ngMZxnBjbL2Ht1RBUvrL6K3X5+l0VeF4qC3g7TKm/a/SGjq12ZD4sc
7rglzjSNlTVSGag6/2WkqxE6HheEBWaloYOdauzwydFNAgMBAAGjEDAOMAwGA1UdEwQFMAMBAf8w
DQYJKoZIhvcNAQELBQADggEBAG88wKjKeTbj5I6wMEvRihd+gWrESJX3bXUSlHWjUfYKcvg3GzM9
cdooscqJdYgN8ezQuYiJQRk7BaPHSlPGkchsPUjvSM6WvIn9IT+VsEuVBrZNbZMSv6lM6wNig3TE
h2OxFTW6Bt8mCZB74EP2wb+39Fr5aJwWvmkxQjct3/O+GYPQhe0Lu1qpbbMhzafYYybSmO+om02V
cTWyJ/vtLUNyGfN7aHyBm6PFE5piAfpBaO9Az+zWil1HOsnzu1tGGnyV6IzQ/UiIo5P2sD8I5lEO
Xdf9Eicy9y5z2Ci2zrmDcAGWL8o5wOWrCqML2ijximFzyQ/swlMC9xBIX9RCFws=
</X509Certificate>
</X509Data>
</KeyInfo>
<Object Id="prop"><SignatureProperties xmlns:dsp="http://www.w3.org/2009/xmldsig-properties"><SignatureProperty Id="profile" Target="#DistributorSignature"><dsp:Profile URI="http://www.w3.org/ns/widgets-digsig#profile"></dsp:Profile></SignatureProperty><SignatureProperty Id="role" Target="#DistributorSignature"><dsp:Role URI="http://www.w3.org/ns/widgets-digsig#role-distributor"></dsp:Role></SignatureProperty><SignatureProperty Id="identifier" Target="#DistributorSignature"><dsp:Identifier></dsp:Identifier></SignatureProperty></SignatureProperties></Object>
</Signature>